model_compression_toolkit/__init__.py
model_compression_toolkit/constants.py
model_compression_toolkit/defaultdict.py
model_compression_toolkit/logger.py
model_compression_toolkit/metadata.py
model_compression_toolkit/verify_packages.py
model_compression_toolkit/core/__init__.py
model_compression_toolkit/core/analyzer.py
model_compression_toolkit/core/graph_prep_runner.py
model_compression_toolkit/core/quantization_prep_runner.py
model_compression_toolkit/core/runner.py
model_compression_toolkit/core/common/__init__.py
model_compression_toolkit/core/common/base_substitutions.py
model_compression_toolkit/core/common/framework_implementation.py
model_compression_toolkit/core/common/framework_info.py
model_compression_toolkit/core/common/memory_computation.py
model_compression_toolkit/core/common/model_builder_mode.py
model_compression_toolkit/core/common/model_collector.py
model_compression_toolkit/core/common/model_validation.py
model_compression_toolkit/core/common/node_prior_info.py
model_compression_toolkit/core/common/similarity_analyzer.py
model_compression_toolkit/core/common/user_info.py
model_compression_toolkit/core/common/back2framework/__init__.py
model_compression_toolkit/core/common/back2framework/base_model_builder.py
model_compression_toolkit/core/common/collectors/__init__.py
model_compression_toolkit/core/common/collectors/base_collector.py
model_compression_toolkit/core/common/collectors/histogram_collector.py
model_compression_toolkit/core/common/collectors/mean_collector.py
model_compression_toolkit/core/common/collectors/min_max_per_channel_collector.py
model_compression_toolkit/core/common/collectors/statistics_collector.py
model_compression_toolkit/core/common/collectors/weighted_histogram_collector.py
model_compression_toolkit/core/common/fusion/__init__.py
model_compression_toolkit/core/common/fusion/fusing_info.py
model_compression_toolkit/core/common/fusion/graph_fuser.py
model_compression_toolkit/core/common/graph/__init__.py
model_compression_toolkit-2.5.1.dist-info/licenses/LICENSE.md
model_compression_toolkit-2.5.1.dist-info/METADATA
model_compression_toolkit-2.5.1.dist-info/WHEEL
model_compression_toolkit-2.5.1.dist-info/top_level.txt
model_compression_toolkit-2.5.1.dist-info/RECORD
