Metadata-Version: 2.4
Name: model_compression_toolkit
Version: 2.5.1
Summary: A Model Compression Toolkit for neural networks
Classifier: Programming Language :: Python :: 3
Classifier: License :: OSI Approved :: Apache Software License
Classifier: Operating System :: OS Independent
Classifier: Topic :: Scientific/Engineering :: Artificial Intelligence
Requires-Python: >=3.10
License-File: LICENSE.md
Requires-Dist: networkx!=2.8.1,<3.6
Requires-Dist: tqdm
Requires-Dist: Pillow
Requires-Dist: numpy
Requires-Dist: scikit-image
Requires-Dist: scikit-learn
Requires-Dist: tensorboard
Requires-Dist: PuLP
Requires-Dist: matplotlib<3.10.0
Requires-Dist: scipy
Requires-Dist: protobuf
Requires-Dist: mct-quantizers==1.6.0
Requires-Dist: pydantic<2.12.0,>=2.0
Requires-Dist: edge-mdt-cl>=1.1
Dynamic: classifier
Dynamic: description
Dynamic: description-content-type
Dynamic: license-file
Dynamic: requires-dist
Dynamic: requires-python
Dynamic: summary
